pfid/__init__.py
pfid/errors.py
pfid/pfid.py
pfid-0.1.0.dist-info/METADATA
pfid-0.1.0.dist-info/WHEEL
pfid-0.1.0.dist-info/RECORD
