Metadata-Version: 2.4
Name: pfid
Version: 0.1.0
Summary: PFID - A ULID-like identifier format with partition support
Author: Prefactor
License-Expression: MIT
Keywords: identifier,partition,pfid,ulid,uuid
Classifier: Development Status :: 4 - Beta
Classifier: Intended Audience :: Developers
Classifier: License :: OSI Approved :: MIT License
Classifier: Programming Language :: Python :: 3
Classifier: Programming Language :: Python :: 3.11
Classifier: Programming Language :: Python :: 3.12
Classifier: Programming Language :: Python :: 3.13
Classifier: Typing :: Typed
Requires-Python: >=3.11
Provides-Extra: dev
Requires-Dist: build>=1.0; extra == 'dev'
Requires-Dist: mypy>=1.14; extra == 'dev'
Requires-Dist: pytest-cov>=6.0; extra == 'dev'
Requires-Dist: pytest>=9.0; extra == 'dev'
Requires-Dist: ruff>=0.9; extra == 'dev'
Requires-Dist: twine>=6.0; extra == 'dev'
